blackstone/__init__.py
blackstone/displacy_palette.py
blackstone/version.py
blackstone/pipeline/__init__.py
blackstone/pipeline/abbreviations.py
blackstone/pipeline/compound_cases.py
blackstone/pipeline/concepts.py
blackstone/pipeline/sentence_segmenter.py
blackstone/rules/__init__.py
blackstone/rules/citation_rules.py
blackstone/rules/concept_rules.py
blackstone/utils/__init__.py
blackstone/utils/legislation_linker.py
blackstone-0.1.15.dist-info/LICENSE
blackstone-0.1.15.dist-info/METADATA
blackstone-0.1.15.dist-info/WHEEL
blackstone-0.1.15.dist-info/top_level.txt
blackstone-0.1.15.dist-info/RECORD
