Metadata-Version: 2.1
Name: blackstone
Version: 0.1.15
Summary: A SpaCy pipeline and models for NLP on unstructured legal text.
Home-page: https://research.iclr.co.uk/blackstone
Author: ICLR&D (Incorporated Council of Law Reporting Research Lab)
Author-email: research@iclr.co.uk
License: Apache
Keywords: law caselaw lawtech legaltech nlp spacy SpaCy biomedical
Platform: UNKNOWN
Classifier: Intended Audience :: Science/Research
Classifier: Development Status :: 3 - Alpha
Classifier: License :: OSI Approved :: Apache Software License
Classifier: Programming Language :: Python :: 3.6
Classifier: Topic :: Scientific/Engineering :: Artificial Intelligence
Requires-Python: >=3.6.0
